CHANGELOG.txt
LICENCE.txt
MANIFEST.in
README.txt
setup.py
GroupCreator/__init__.py
GroupCreator.egg-info/PKG-INFO
GroupCreator.egg-info/SOURCES.txt
GroupCreator.egg-info/dependency_links.txt
GroupCreator.egg-info/top_level.txt