Metadata-Version: 1.1
Name: GroupCreator
Version: 0.0.2
Summary: A package that creates groups for you.
Home-page: https://picstreme.com/
Author: DefaultGamingChannel
Author-email: info@picstreme.com
License: MIT
Keywords: groups
Platform: UNKNOWN
Classifier: Development Status :: 2 - Pre-Alpha
Classifier: Intended Audience :: Education
Classifier: Operating System :: Microsoft :: Windows :: Windows 10
Classifier: License :: OSI Approved :: MIT License
Classifier: Programming Language :: Python :: 3
